cronpulse_lib/__init__.py
cronpulse_lib/client.py
cronpulse_lib/py.typed
cronpulse_lib-0.1.9.dist-info/METADATA
cronpulse_lib-0.1.9.dist-info/WHEEL
cronpulse_lib-0.1.9.dist-info/top_level.txt
cronpulse_lib-0.1.9.dist-info/RECORD
